messaging/__init__.py
byteline_sdk-1.0.2.dist-info/LICENSE
byteline_sdk-1.0.2.dist-info/METADATA
byteline_sdk-1.0.2.dist-info/WHEEL
byteline_sdk-1.0.2.dist-info/top_level.txt
byteline_sdk-1.0.2.dist-info/RECORD
