Metadata-Version: 2.1
Name: byteline-sdk
Version: 1.0.2
Summary: Package to easily use Byteline REST APIs
Home-page: https://github.com/byteline/byteline-py-sdk
Author: Devinder Singh
Author-email: dsingh@byteline.io
License: UNKNOWN
Platform: UNKNOWN
Classifier: Programming Language :: Python :: 3
Classifier: License :: OSI Approved :: MIT License
Classifier: Operating System :: OS Independent
Requires-Python: >=3.6
Requires-Dist: requests
